{"file:///d%3A/PROJECTS/full%20stack/E-Com/admin/app/globals.css":{"language":"PostCSS","code":57,"comment":0,"blank":6},"file:///d%3A/PROJECTS/full%20stack/E-Com/admin/app/components/useSession.js":{"language":"JavaScript","code":3,"comment":0,"blank":0},"file:///d%3A/PROJECTS/full%20stack/E-Com/admin/app/components/layout.js":{"language":"JavaScript","code":31,"comment":0,"blank":2},"file:///d%3A/PROJECTS/full%20stack/E-Com/admin/app/components/ProductForm.js":{"language":"JavaScript","code":216,"comment":4,"blank":13},"file:///d%3A/PROJECTS/full%20stack/E-Com/admin/app/components/SessionProvider.js":{"language":"JavaScript","code":3,"comment":0,"blank":0},"file:///d%3A/PROJECTS/full%20stack/E-Com/admin/app/components/DataContext.js":{"language":"JavaScript","code":14,"comment":0,"blank":5},"file:///d%3A/PROJECTS/full%20stack/E-Com/admin/app/components/Navbar.js":{"language":"JavaScript","code":54,"comment":1,"blank":3},"file:///d%3A/PROJECTS/full%20stack/E-Com/admin/app/settings/page.js":{"language":"JavaScript","code":9,"comment":0,"blank":2},"file:///d%3A/PROJECTS/full%20stack/E-Com/admin/app/page.js":{"language":"JavaScript","code":28,"comment":0,"blank":3},"file:///d%3A/PROJECTS/full%20stack/E-Com/admin/app/layout.js":{"language":"JavaScript","code":22,"comment":0,"blank":3},"file:///d%3A/PROJECTS/full%20stack/E-Com/admin/app/products/page.js":{"language":"JavaScript","code":53,"comment":0,"blank":2},"file:///d%3A/PROJECTS/full%20stack/E-Com/admin/app/orders/page.js":{"language":"JavaScript","code":9,"comment":0,"blank":2},"file:///d%3A/PROJECTS/full%20stack/E-Com/admin/app/products/new/page.js":{"language":"JavaScript","code":10,"comment":0,"blank":1},"file:///d%3A/PROJECTS/full%20stack/E-Com/admin/app/products/edit/%5B...id%5D/page.js":{"language":"JavaScript","code":27,"comment":1,"blank":1},"file:///d%3A/PROJECTS/full%20stack/E-Com/admin/app/products/delete/%5B...id%5D/page.js":{"language":"JavaScript","code":44,"comment":0,"blank":1},"file:///d%3A/PROJECTS/full%20stack/E-Com/admin/app/categories/page.js":{"language":"JavaScript","code":181,"comment":1,"blank":15},"file:///d%3A/PROJECTS/full%20stack/E-Com/admin/app/api/upload/route.js":{"language":"JavaScript","code":50,"comment":1,"blank":7},"file:///d%3A/PROJECTS/full%20stack/E-Com/admin/app/api/products/route.js":{"language":"JavaScript","code":56,"comment":2,"blank":6},"file:///d%3A/PROJECTS/full%20stack/E-Com/admin/app/api/categories/route.js":{"language":"JavaScript","code":31,"comment":2,"blank":5},"file:///d%3A/PROJECTS/full%20stack/E-Com/admin/app/api/auth/%5B...nextauth%5D/route.js":{"language":"JavaScript","code":12,"comment":0,"blank":2}}